AsyncPQ/ASPQ_Wrapper.py
AsyncPQ/AsyncQueue.py
AsyncPQ/__init__.py
AsyncPQ-0.44.dist-info/DESCRIPTION.rst
AsyncPQ-0.44.dist-info/METADATA
AsyncPQ-0.44.dist-info/RECORD
AsyncPQ-0.44.dist-info/WHEEL
AsyncPQ-0.44.dist-info/metadata.json
AsyncPQ-0.44.dist-info/top_level.txt
